juandb/__init__.py
juandb/client/__init__.py
juandb/client/base.py
juandb/client/exceptions.py
juandb/client/main.py
juandb/const/__init__.py
juandb/const/bahador_const.py
juandb/const/wallex_const.py
juandb-0.2.2.dist-info/METADATA
juandb-0.2.2.dist-info/WHEEL
juandb-0.2.2.dist-info/top_level.txt
juandb-0.2.2.dist-info/RECORD
