Metadata-Version: 2.1
Name: juandb
Version: 0.2.2
Summary: Nice
Home-page: https://github.com/amiwrpremium/juan
Author: amiwrpremium
Author-email: amiwrpremium@gmail.com
License: MIT
Project-URL: Bug Tracker, https://github.com/amiwrpremium/juan/issues
Keywords: NICE,JUAN
Classifier: Development Status :: 3 - Alpha
Classifier: Intended Audience :: Developers
Classifier: Topic :: Software Development :: Build Tools
Classifier: License :: OSI Approved :: MIT License
Classifier: Programming Language :: Python :: 3
Classifier: Programming Language :: Python :: 3.4
Classifier: Programming Language :: Python :: 3.5
Classifier: Programming Language :: Python :: 3.6
Classifier: Programming Language :: Python :: 3.7
Classifier: Programming Language :: Python :: 3.8
Classifier: Programming Language :: Python :: 3.9
Requires-Python: >=3.6
Requires-Dist: requests
Requires-Dist: aiohttp
Requires-Dist: pydantic
